finance_trading_ai_agents_mcp/__init__.py
finance_trading_ai_agents_mcp/__main__.py
finance_trading_ai_agents_mcp/mcp_cli.py
finance_trading_ai_agents_mcp/mcp_manage.py
finance_trading_ai_agents_mcp/addition_custom_mcp/addition_custom_mcp_interface.py
finance_trading_ai_agents_mcp/assistive_tools/aitrados_mcp_client.py
finance_trading_ai_agents_mcp/assistive_tools/assistive_tools_utils.py
finance_trading_ai_agents_mcp/assistive_tools/mcp_tools_converter.py
finance_trading_ai_agents_mcp/assistive_tools/basic_system_function_call_prompt_words/de.md
finance_trading_ai_agents_mcp/assistive_tools/basic_system_function_call_prompt_words/en.md
finance_trading_ai_agents_mcp/assistive_tools/basic_system_function_call_prompt_words/es.md
finance_trading_ai_agents_mcp/assistive_tools/basic_system_function_call_prompt_words/fr.md
finance_trading_ai_agents_mcp/assistive_tools/basic_system_function_call_prompt_words/ja.md
finance_trading_ai_agents_mcp/assistive_tools/basic_system_function_call_prompt_words/kr.md
finance_trading_ai_agents_mcp/assistive_tools/basic_system_function_call_prompt_words/ru.md
finance_trading_ai_agents_mcp/assistive_tools/basic_system_function_call_prompt_words/zh_cn.md
finance_trading_ai_agents_mcp/assistive_tools/basic_system_function_call_prompt_words/zh_tw.md
finance_trading_ai_agents_mcp/live_streaming_ohlc_operations/live_streaming_ohlc_operation.py
finance_trading_ai_agents_mcp/mcp_result_control/common_control.py
finance_trading_ai_agents_mcp/mcp_result_control/control_mixin.py
finance_trading_ai_agents_mcp/mcp_services/addition_custom_mcp_tool.py
finance_trading_ai_agents_mcp/mcp_services/economic_calendar_service.py
finance_trading_ai_agents_mcp/mcp_services/global_instance.py
finance_trading_ai_agents_mcp/mcp_services/http_service.py
finance_trading_ai_agents_mcp/mcp_services/index.html
finance_trading_ai_agents_mcp/mcp_services/mcp_instance.py
finance_trading_ai_agents_mcp/mcp_services/news_service.py
finance_trading_ai_agents_mcp-0.0.92.dist-info/METADATA
finance_trading_ai_agents_mcp-0.0.92.dist-info/WHEEL
finance_trading_ai_agents_mcp-0.0.92.dist-info/entry_points.txt
finance_trading_ai_agents_mcp-0.0.92.dist-info/RECORD
