Metadata-Version: 2.4
Name: finance-trading-ai-agents-mcp
Version: 0.0.92
Summary: A free, specialized MCP server for financial analysis and quantitative trading. Provides one-click setup for local financial MCP services with department-based architecture simulating financial company operations. Supports traditional indicators, price action analysis, economic calendar, fundamental analysis, and news integration for seamless LLM interaction and algorithmic trading.
Project-URL: Homepage, https://github.com/aitrados/finance-trading-ai-agents-mcp
Project-URL: Bug Tracker, https://github.com/aitrados/finance-trading-ai-agents-mcp/issues
Project-URL: Repository, https://github.com/aitrados/finance-trading-ai-agents-mcp
Author-email: Alexander <support@aitrados.com>
License: MIT License
Keywords: ai mcp,ai trading,finance agent,finance mcp,financial mcp,streaming ohlc,trading mcp
Classifier: Environment :: Console
Classifier: Environment :: Web Environment
Classifier: Intended Audience :: Developers
Classifier: Intended Audience :: Financial and Insurance Industry
Classifier: License :: OSI Approved :: MIT License
Classifier: Operating System :: OS Independent
Classifier: Programming Language :: Python :: 3
Classifier: Programming Language :: Python :: 3.10
Classifier: Programming Language :: Python :: 3.11
Classifier: Programming Language :: Python :: 3.12
Classifier: Programming Language :: Python :: 3.13
Classifier: Programming Language :: Python :: 3.14
Classifier: Topic :: Office/Business :: Financial
Classifier: Topic :: Office/Business :: Financial :: Investment
Classifier: Topic :: Scientific/Engineering :: Information Analysis
Classifier: Topic :: Software Development :: Libraries :: Python Modules
Requires-Python: >=3.10
Requires-Dist: aitrados-api>=0.1.97
Requires-Dist: aitrados-broker>=0.0.17
Requires-Dist: fastapi
Requires-Dist: fastmcp
